repvar/__init__.py
repvar/__main__.py
repvar-0.1.221.dist-info/METADATA
repvar-0.1.221.dist-info/WHEEL
repvar-0.1.221.dist-info/entry_points.txt
repvar-0.1.221.dist-info/licenses/LICENSE
repvar-0.1.221.dist-info/RECORD
