Metadata-Version: 2.4
Name: repvar
Version: 0.1.221
Summary: Easily replace variables within file contents and filenames!
Project-URL: Homepage, https://github.com/vamanfredi/repvar
Author-email: Valentin Manfredi <vamanfredi@frba.utn.edu.ar>
License-File: LICENSE
Classifier: Environment :: Console
Classifier: License :: OSI Approved :: MIT License
Classifier: Topic :: Text Processing
Classifier: Topic :: Utilities
Requires-Python: >=3.12
Requires-Dist: typer>=0.15.1
